groklib/cli.py
groklib/grok.py
groklib-0.0.1.dist-info/METADATA
groklib-0.0.1.dist-info/WHEEL
groklib-0.0.1.dist-info/entry_points.txt
groklib-0.0.1.dist-info/top_level.txt
groklib-0.0.1.dist-info/RECORD
